LICENSE
README.md
setup.py
src/PyFADO.egg-info/PKG-INFO
src/PyFADO.egg-info/SOURCES.txt
src/PyFADO.egg-info/dependency_links.txt
src/PyFADO.egg-info/requires.txt
src/PyFADO.egg-info/top_level.txt
src/python/PlotFADOv01.py
src/python/ReadFADOFitsv01.py
src/python/__init__.py