Metadata-Version: 2.1
Name: PyFADO
Version: 0.0.1
Summary: PyFADO is in beta version.
Home-page: https://github.com/neutrinomuon/PyFADO
Author: Jean Gomes
Author-email: antineutrinomuon@gmail.com
Classifier: Programming Language :: Python :: 3
Classifier: Operating System :: OS Independent
License-File: LICENSE
